ecpcgrading/__init__.py
ecpcgrading/assignments.py
ecpcgrading/canvas.py
ecpcgrading/config.py
ecpcgrading/grading_tool.tcss
ecpcgrading/students.py
ecpcgrading/tasks.py
ecpcgrading/tui.py
ecpcgrading-1.7.1.dist-info/METADATA
ecpcgrading-1.7.1.dist-info/WHEEL
ecpcgrading-1.7.1.dist-info/entry_points.txt
ecpcgrading-1.7.1.dist-info/licenses/LICENSE
ecpcgrading-1.7.1.dist-info/RECORD
