Metadata-Version: 2.4
Name: ecpcgrading
Version: 1.7.1
Summary: Code grading tool for ECPC
Author-email: David Fokkema <davidfokkema@icloud.com>
License-File: LICENSE
Requires-Python: >=3.10
Requires-Dist: canvas-course-tools>=0.12.0
Requires-Dist: click>=8.1.8
Requires-Dist: humanize>=4.11.0
Requires-Dist: pydantic>=2.10.6
Requires-Dist: python-slugify>=8.0.4
Requires-Dist: textual>=2.1.0
Requires-Dist: tomli>=2.2.1; python_full_version < '3.11'
Requires-Dist: unidecode>=1.3.8
